vital_ai_domain/__init__.py
vital_ai_domain/model/Account.py
vital_ai_domain/model/Account.pyi
vital_ai_domain/model/AdminLogin.py
vital_ai_domain/model/AdminLogin.pyi
vital_ai_domain/model/BusinessOrganization.py
vital_ai_domain/model/BusinessOrganization.pyi
vital_ai_domain/model/CredentialsLogin.py
vital_ai_domain/model/CredentialsLogin.pyi
vital_ai_domain/model/Currency.py
vital_ai_domain/model/Currency.pyi
vital_ai_domain/model/DatascriptInfo.py
vital_ai_domain/model/DatascriptInfo.pyi
vital_ai_domain/model/DatascriptRun.py
vital_ai_domain/model/DatascriptRun.pyi
vital_ai_domain/model/DomainOntology.py
vital_ai_domain/model/Duration.py
vital_ai_domain/model/Duration.pyi
vital_ai_domain/model/Edge_hasLoginAuth.py
vital_ai_domain/model/Edge_hasLoginAuth.pyi
vital_ai_domain/model/Edge_hasNextElement.py
vital_ai_domain/model/Edge_hasNextElement.pyi
vital_ai_domain/model/Edge_hasUserLogin.py
vital_ai_domain/model/Edge_hasUserLogin.pyi
vital_ai_domain/model/Edge_hasUserSession.py
vital_ai_domain/model/Edge_hasUserSession.pyi
vital_ai_domain/model/Edge_hasVitalOntNode.py
vital_ai_domain/model/Edge_hasVitalOntNode.pyi
vital_ai_domain/model/EmailAddress.py
vital_ai_domain/model/EmailAddress.pyi
vital_ai_domain/model/ErrorFact.py
vital_ai_domain/model/ErrorFact.pyi
vital_ai_domain/model/FileNode.py
vital_ai_domain/model/FileNode.pyi
vital_ai_domain/model/GeographicRegion.py
vital_ai_domain/model/GeographicRegion.pyi
vital_ai_domain/model/GovernmentOrganization.py
vital_ai_domain/model/GovernmentOrganization.pyi
vital_ai_domain/model/HyperEdge_hasFact.py
vital_ai_domain/model/HyperEdge_hasFact.pyi
vital_ai_domain/model/HyperEdge_hasHyperAnnotation.py
vital_ai_domain/model/HyperEdge_hasHyperAnnotation.pyi
vital_ai_domain/model/HyperEdge_hasReason.py
vital_ai_domain/model/HyperEdge_hasReason.pyi
vital_ai_domain/model/Identifier_Locator.py
vital_ai_domain/model/Identifier_Locator.pyi
vital_ai_domain/model/Job.py
vital_ai_domain/model/Job.pyi
vital_ai_domain-0.1.7.dist-info/LICENSE
vital_ai_domain-0.1.7.dist-info/METADATA
vital_ai_domain-0.1.7.dist-info/WHEEL
vital_ai_domain-0.1.7.dist-info/entry_points.txt
vital_ai_domain-0.1.7.dist-info/top_level.txt
vital_ai_domain-0.1.7.dist-info/RECORD
