Metadata-Version: 2.1
Name: vital-ai-domain
Version: 0.1.7
Summary: VitalSigns vital domain
Home-page: https://github.com/vital-ai/vitalhome-knowledge-graph
Author: Marc Hadfield
Author-email: marc@vital.ai
License: Apache License 2.0
Classifier: Programming Language :: Python :: 3.10
Classifier: License :: OSI Approved :: Apache Software License
Classifier: Operating System :: OS Independent
Requires-Python: >=3.10
License-File: LICENSE
Requires-Dist: vital-ai-vitalsigns >=0.1.19
